[
  {
    "EntityID": "1",
    "SubjectId": "1",
    "isAlert": true
  },
  {
    "EntityID": "2",
    "SubjectId": "2",
    "isAlert": false
  },
  {
    "EntityID": "3",
    "SubjectId": "3",
    "isAlert": true
  },
  {
    "EntityID": "4",
    "SubjectId": "4",
    "isAlert": false
  },
  {
    "EntityID": "5",
    "SubjectId": "5",
    "isAlert": true
  },
  {
    "EntityID": "6",
    "SubjectId": "6",
    "isAlert": false
  },
  {
    "EntityID": "7",
    "SubjectId": "7",
    "isAlert": true
  },
  {
    "EntityID": "8",
    "SubjectId": "8",
    "isAlert": false
  },
  {
    "EntityID": "9",
    "SubjectId": "9",
    "isAlert": true
  },
  {
    "EntityID": "10",
    "SubjectId": "10",
    "isAlert": false
  },
  {
    "EntityID": "11",
    "SubjectId": "1",
    "isAlert": true
  },
  {
    "EntityID": "12",
    "SubjectId": "2",
    "isAlert": false
  },
  {
    "EntityID": "13",
    "SubjectId": "3",
    "isAlert": true
  },
  {
    "EntityID": "14",
    "SubjectId": "4",
    "isAlert": false
  },
  {
    "EntityID": "15",
    "SubjectId": "5",
    "isAlert": true
  }
]
